wcferry/DISCLAIMER.md
wcferry/__init__.py
wcferry/client.py
wcferry/sdk.dll
wcferry/spy.dll
wcferry/spy_debug.dll
wcferry/wcf_pb2.py
wcferry/wxmsg.py
wcferry-39.5.1.0.dist-info/METADATA
wcferry-39.5.1.0.dist-info/WHEEL
wcferry-39.5.1.0.dist-info/top_level.txt
wcferry-39.5.1.0.dist-info/RECORD
