Metadata-Version: 2.4
Name: wcferry
Version: 39.5.1.0
Summary: 一个玩微信的工具
Home-page: https://github.com/lich0821/WeChatFerry
Author: Changhua
Author-email: lichanghua0821@gmail.com
License: MIT
Project-URL: Documentation, https://wechatferry.readthedocs.io/zh/latest/index.html
Project-URL: GitHub, https://github.com/lich0821/WeChatFerry/
Classifier: Environment :: Win32 (MS Windows)
Classifier: Intended Audience :: Developers
Classifier: Intended Audience :: Customer Service
Classifier: Topic :: Communications :: Chat
Classifier: Operating System :: Microsoft :: Windows
Classifier: Programming Language :: Python
Requires-Python: >=3.8
Requires-Dist: setuptools
Requires-Dist: grpcio-tools
Requires-Dist: pynng
Requires-Dist: requests
Dynamic: author
Dynamic: author-email
Dynamic: classifier
Dynamic: description
Dynamic: description-content-type
Dynamic: home-page
Dynamic: license
Dynamic: project-url
Dynamic: requires-dist
Dynamic: requires-python
Dynamic: summary
